.coveragerc
LICENSE
MANIFEST.in
README.rst
setup.py
tox.ini
docs/Makefile
docs/build/doctrees/environment.pickle
docs/build/doctrees/index.doctree
docs/build/html/.buildinfo
docs/build/html/genindex.html
docs/build/html/index.html
docs/build/html/objects.inv
docs/build/html/search.html
docs/build/html/searchindex.js
docs/build/html/_sources/index.txt
docs/build/html/_static/ajax-loader.gif
docs/build/html/_static/basic.css
docs/build/html/_static/comment-bright.png
docs/build/html/_static/comment-close.png
docs/build/html/_static/comment.png
docs/build/html/_static/default.css
docs/build/html/_static/doctools.js
docs/build/html/_static/down-pressed.png
docs/build/html/_static/down.png
docs/build/html/_static/file.png
docs/build/html/_static/jquery.js
docs/build/html/_static/minus.png
docs/build/html/_static/plus.png
docs/build/html/_static/pygments.css
docs/build/html/_static/searchtools.js
docs/build/html/_static/sidebar.js
docs/build/html/_static/underscore.js
docs/build/html/_static/up-pressed.png
docs/build/html/_static/up.png
docs/build/html/_static/websupport.js
docs/source/api.rst
docs/source/changelog.rst
docs/source/conf.py
docs/source/extending.rst
docs/source/guide.rst
docs/source/index.rst
docs/source/notes.rst
docs/source/types.rst
teleport/__init__.py
teleport/compat.py
teleport/core.py
teleport/examples.py
teleport.egg-info/PKG-INFO
teleport.egg-info/SOURCES.txt
teleport.egg-info/dependency_links.txt
teleport.egg-info/requires.txt
teleport.egg-info/top_level.txt
teleport/testsuite/__init__.py
teleport/testsuite/test_core.py
teleport/testsuite/test_custom_types.py