Metadata-Version: 1.1
Name: teleport
Version: 0.4.0
Summary: Lightweight JSON type system
Home-page: http://teleport-json.org
Author: Alexei Boronine
Author-email: alexei@boronine.com
License: MIT
Platform: UNKNOWN
Classifier: Development Status :: 4 - Beta
Classifier: Programming Language :: Python :: 2
Classifier: Programming Language :: Python :: 3
